.gitignore
changelog.txt
fswalk.py
license.txt
lsext.py
readme.md
setup.py
lsext.egg-info/PKG-INFO
lsext.egg-info/SOURCES.txt
lsext.egg-info/dependency_links.txt
lsext.egg-info/entry_points.txt
lsext.egg-info/pbr.json
lsext.egg-info/top_level.txt