Metadata-Version: 1.1
Name: lsext
Version: 0.1.0
Summary: File Extension Distribution Analysis
Home-page: https://github.com/NoviceLive/lsext
Author: Gu Zhengxiong
Author-email: rectigu@gmail.com
License: GPL
Keywords: List Extensions,Traverse Directories
Platform: UNKNOWN
Classifier: Development Status :: 3 - Alpha
Classifier: Programming Language :: Python :: 2
Classifier: Programming Language :: Python :: 3
